smyth/__about__.py
smyth/__init__.py
smyth/__main__.py
smyth/config.py
smyth/context.py
smyth/event.py
smyth/exceptions.py
smyth/py.typed
smyth/smyth.py
smyth/types.py
smyth/utils.py
smyth/runner/__init__.py
smyth/runner/fake_context.py
smyth/runner/process.py
smyth/runner/strategy.py
smyth/server/__init__.py
smyth/server/app.py
smyth/server/endpoints.py
smyth-0.7.0.post1.dist-info/METADATA
smyth-0.7.0.post1.dist-info/WHEEL
smyth-0.7.0.post1.dist-info/licenses/LICENSE.txt
smyth-0.7.0.post1.dist-info/RECORD
