Metadata-Version: 2.4
Name: smyth
Version: 0.7.0.post1
Summary: Smyth is a versatile tool designed to enhance your AWS Lambda development experience. It is a pure Python tool that allows for easy customization and state persistence, making your Lambda development more efficient and developer-friendly.
Project-URL: Documentation, https://mirumee.github.io/smyth/
Project-URL: Issues, https://github.com/mirumee/smyth/issues
Project-URL: Source, https://github.com/mirumee/smyth
Author-email: Mirumee <hello@mirumee.com>
License-Expression: BSD-3-Clause
License-File: LICENSE.txt
Classifier: Development Status :: 4 - Beta
Classifier: Environment :: Console
Classifier: Intended Audience :: Developers
Classifier: Programming Language :: Python
Classifier: Programming Language :: Python :: 3.10
Classifier: Programming Language :: Python :: 3.11
Classifier: Programming Language :: Python :: 3.12
Classifier: Programming Language :: Python :: 3.13
Classifier: Programming Language :: Python :: Implementation :: CPython
Classifier: Topic :: Internet :: WWW/HTTP :: HTTP Servers
Classifier: Topic :: Software Development
Classifier: Topic :: Software Development :: Build Tools
Classifier: Topic :: Software Development :: Libraries :: Python Modules
Requires-Python: >=3.10
Requires-Dist: asgiref
Requires-Dist: aws-lambda-powertools
Requires-Dist: click
Requires-Dist: pydantic
Requires-Dist: rich
Requires-Dist: setproctitle
Requires-Dist: starlette
Requires-Dist: toml
Requires-Dist: typer
Requires-Dist: uvicorn
Provides-Extra: dev
Requires-Dist: ipdb; extra == 'dev'
Provides-Extra: docs
Requires-Dist: mkdocs-material~=9.0; extra == 'docs'
Requires-Dist: termynal; extra == 'docs'
Provides-Extra: types
Requires-Dist: mypy>=1.0.0; extra == 'types'
Requires-Dist: pytest; extra == 'types'
Requires-Dist: pytest-asyncio; extra == 'types'
Requires-Dist: types-toml; extra == 'types'
